[{"name": "Summary", "link": "https://research.alexparsons.co.uk/political-equality/#summary", "children": []}, {"name": "Introduction", "link": "https://research.alexparsons.co.uk/political-equality/#introduction", "children": []}, {"name": "Universal Suffrage", "link": "https://research.alexparsons.co.uk/political-equality/#universal-suffrage", "children": []}, {"name": "Equal Shares", "link": "https://research.alexparsons.co.uk/political-equality/#equal-shares", "children": []}, {"name": "Independence", "link": "https://research.alexparsons.co.uk/political-equality/#independence", "children": [{"name": "Equal probabilities", "link": "https://research.alexparsons.co.uk/political-equality/#equal-probabilities", "children": []}, {"name": "Anonymity", "link": "https://research.alexparsons.co.uk/political-equality/#anonymity", "children": []}, {"name": "Majority Rule", "link": "https://research.alexparsons.co.uk/political-equality/#majority-rule", "children": []}]}, {"name": "Proportional Representation", "link": "https://research.alexparsons.co.uk/political-equality/#proportional-representation", "children": []}, {"name": "Other considerations", "link": "https://research.alexparsons.co.uk/political-equality/#other-considerations", "children": []}]